sanic_dispatcher/__init__.py
sanic_dispatcher/extension.py
sanic_dispatcher/version.py
Sanic_Dispatcher-0.8.0.0.dist-info/LICENCE
Sanic_Dispatcher-0.8.0.0.dist-info/METADATA
Sanic_Dispatcher-0.8.0.0.dist-info/WHEEL
Sanic_Dispatcher-0.8.0.0.dist-info/top_level.txt
Sanic_Dispatcher-0.8.0.0.dist-info/RECORD
