Metadata-Version: 2.1
Name: Sanic-Dispatcher
Version: 0.8.0.0
Summary: Multi-application dispatcher based on DispatcherMiddleware from the Werkzeug Project.
Home-page: https://github.com/ashleysommer/sanic-dispatcher
Author: Ashley Sommer
Author-email: ashleysommer@gmail.com
License: MIT
Platform: any
Classifier: Environment :: Web Environment
Classifier: Intended Audience :: Developers
Classifier: License :: OSI Approved :: MIT License
Classifier: Operating System :: OS Independent
Classifier: Programming Language :: Python
Classifier: Programming Language :: Python :: 3
Classifier: Programming Language :: Python :: 3 :: Only
Classifier: Programming Language :: Python :: Implementation :: CPython
Classifier: Programming Language :: Python :: Implementation :: PyPy
Classifier: Topic :: Internet :: WWW/HTTP :: Dynamic Content
Classifier: Topic :: Software Development :: Libraries :: Python Modules
Requires-Dist: sanic (>=0.7.0)
